ported/Client.py
ported/Server.py
ported/__init__.py
ported-0.2.1.dist-info/WHEEL
ported-0.2.1.dist-info/METADATA
ported-0.2.1.dist-info/RECORD
