Metadata-Version: 2.1
Name: ported
Version: 0.2.1
Summary: port forword website for any 
Author: ported
Author-email: shahinmondal42bd@gmail.com
Requires-Python: >=3.10,<4.0
Classifier: Programming Language :: Python :: 3
Classifier: Programming Language :: Python :: 3.10
Requires-Dist: pendulum (>=2.1.2,<3.0.0)
